MANIFEST.in
README.md
setup.py
Flask_Swag.egg-info/PKG-INFO
Flask_Swag.egg-info/SOURCES.txt
Flask_Swag.egg-info/dependency_links.txt
Flask_Swag.egg-info/not-zip-safe
Flask_Swag.egg-info/requires.txt
Flask_Swag.egg-info/top_level.txt
flask_swag/__init__.py
flask_swag/core.py
flask_swag/ext.py
flask_swag/fields.py
flask_swag/globals.py
flask_swag/mark.py
flask_swag/schemas.py
flask_swag/utils.py
flask_swag/version.py
flask_swag/extractor/__init__.py
flask_swag/extractor/base.py
flask_swag/extractor/mark.py
flask_swag/resources/swagger-ui/.gitignore
flask_swag/resources/swagger-ui/index.html
flask_swag/resources/swagger-ui/o2c.html
flask_swag/resources/swagger-ui/swagger-ui.js
flask_swag/resources/swagger-ui/swagger-ui.min.js
flask_swag/resources/swagger-ui/css/print.css
flask_swag/resources/swagger-ui/css/reset.css
flask_swag/resources/swagger-ui/css/screen.css
flask_swag/resources/swagger-ui/css/style.css
flask_swag/resources/swagger-ui/css/typography.css
flask_swag/resources/swagger-ui/fonts/DroidSans-Bold.ttf
flask_swag/resources/swagger-ui/fonts/DroidSans.ttf
flask_swag/resources/swagger-ui/images/collapse.gif
flask_swag/resources/swagger-ui/images/expand.gif
flask_swag/resources/swagger-ui/images/explorer_icons.png
flask_swag/resources/swagger-ui/images/favicon-16x16.png
flask_swag/resources/swagger-ui/images/favicon-32x32.png
flask_swag/resources/swagger-ui/images/favicon.ico
flask_swag/resources/swagger-ui/images/logo_small.png
flask_swag/resources/swagger-ui/images/pet_store_api.png
flask_swag/resources/swagger-ui/images/throbber.gif
flask_swag/resources/swagger-ui/images/wordnik_api.png
flask_swag/resources/swagger-ui/lang/en.js
flask_swag/resources/swagger-ui/lang/es.js
flask_swag/resources/swagger-ui/lang/fr.js
flask_swag/resources/swagger-ui/lang/it.js
flask_swag/resources/swagger-ui/lang/ja.js
flask_swag/resources/swagger-ui/lang/pl.js
flask_swag/resources/swagger-ui/lang/pt.js
flask_swag/resources/swagger-ui/lang/ru.js
flask_swag/resources/swagger-ui/lang/tr.js
flask_swag/resources/swagger-ui/lang/translator.js
flask_swag/resources/swagger-ui/lang/zh-cn.js
flask_swag/resources/swagger-ui/lib/backbone-min.js
