Metadata-Version: 1.1
Name: Flask-Swag
Version: 0.1.2
Summary: Build swagger spec with Flask.
Home-page: https://github.com/hardtack/flask-swag
Author: Choi Geonu
Author-email: 6566gun@gmail.com
License: MIT License
Platform: UNKNOWN
Classifier: Intended Audience :: Developers
Classifier: License :: OSI Approved :: MIT License
Classifier: Programming Language :: Python :: 3.4
Classifier: Programming Language :: Python :: 3.5
